hermes/__init__.py
hermes/config.json
hermes/hermes.py
hermes_tod-2.0.dist-info/METADATA
hermes_tod-2.0.dist-info/WHEEL
hermes_tod-2.0.dist-info/entry_points.txt
hermes_tod-2.0.dist-info/RECORD
