Metadata-Version: 2.4
Name: hermes-tod
Version: 2.0
Summary: Hermes is a powerful, automated tool designed for detecting Cross-Site Scripting (XSS) vulnerabilities in web applications. It integrates multiple open-source tools and custom techniques to perform comprehensive scanning, including DOM-based XSS detection, payload mutation, and HTTP parameter pollution testing. With features like parallel processing, smart filtering, and detailed reporting, Hermes is ideal for security researchers and penetration testers.
Project-URL: Homepage, https://github.com/joelindra/Hermes
Project-URL: Issues, https://github.com/joelindra/Hermes/issues
Author-email: Joel Indra <anonre@anonre.com>
Classifier: License :: OSI Approved :: MIT License
Classifier: Operating System :: OS Independent
Classifier: Programming Language :: Python :: 3
Requires-Python: >=3.7
